CHANGES.rst
MANIFEST.in
README.rst
setup.py
django_sizedimagefield.egg-info/PKG-INFO
django_sizedimagefield.egg-info/SOURCES.txt
django_sizedimagefield.egg-info/dependency_links.txt
django_sizedimagefield.egg-info/not-zip-safe
django_sizedimagefield.egg-info/top_level.txt
sizedimagefield/__init__.py
sizedimagefield/fields.py