Metadata-Version: 1.1
Name: django-sizedimagefield
Version: 0.1.1
Summary: A very simple Django field to resize images at upload.
Home-page: http://github.com/makinacorpus/django-sizedimagefield
Author: Gagaro
Author-email: yann.fouillat@makina-corpus.com
License: BSD
Keywords: django sized image resize thumbnail
Platform: UNKNOWN
Classifier: License :: OSI Approved :: BSD License
Classifier: Framework :: Django
Classifier: Framework :: Django :: 1.11
Classifier: Programming Language :: Python :: 3.6
